CHANGELOG
LICENSE
MANIFEST.in
README.rst
setup.py
django_jpic_jfu.egg-info/PKG-INFO
django_jpic_jfu.egg-info/SOURCES.txt
django_jpic_jfu.egg-info/dependency_links.txt
django_jpic_jfu.egg-info/top_level.txt
jfu/__init__.py
jfu/http.py
jfu/static/cors/postmessage.html
jfu/static/cors/result.html
jfu/static/css/demo-ie8.css
jfu/static/css/demo.css
jfu/static/css/jquery.fileupload-noscript.css
jfu/static/css/jquery.fileupload-ui-noscript.css
jfu/static/css/jquery.fileupload-ui.css
jfu/static/css/jquery.fileupload.css
jfu/static/css/style.css
jfu/static/demo/blueimp-gallery.min.css
jfu/static/demo/canvas-to-blob.min.js
jfu/static/demo/jquery.blueimp-gallery.min.js
jfu/static/demo/load-image.min.js
jfu/static/demo/tmpl.min.js
jfu/static/img/error.png
jfu/static/img/error.svg
jfu/static/img/loading.gif
jfu/static/img/play-pause.png
jfu/static/img/play-pause.svg
jfu/static/img/progressbar.gif
jfu/static/img/video-play.png
jfu/static/img/video-play.svg
jfu/static/js/app.js
jfu/static/js/jquery.fileupload-angular.js
jfu/static/js/jquery.fileupload-audio.js
jfu/static/js/jquery.fileupload-image.js
jfu/static/js/jquery.fileupload-jquery-ui.js
jfu/static/js/jquery.fileupload-process.js
jfu/static/js/jquery.fileupload-ui.js
jfu/static/js/jquery.fileupload-validate.js
jfu/static/js/jquery.fileupload-video.js
jfu/static/js/jquery.fileupload.js
jfu/static/js/jquery.iframe-transport.js
jfu/static/js/main.js
jfu/static/js/cors/jquery.postmessage-transport.js
jfu/static/js/cors/jquery.xdr-transport.js
jfu/static/js/vendor/jquery.ui.widget.js
jfu/templates/jfu/upload_form.html
jfu/templatetags/__init__.py
jfu/templatetags/jfutags.py